.coveragerc
.gitattributes
AUTHORS.rst
CHANGES.rst
LICENSE.txt
MANIFEST.in
README.rst
jss.json
requirements.txt
setup.cfg
setup.py
test-requirements.txt
versioneer.py
cppa3/__init__.py
cppa3/_version.py
cppa3/cpa2.py
cppa3/cppa23.py
cppa3/index.py
cppa3/match.py
cppa3/pmode.py
cppa3/profile.py
cppa3/schema.py
cppa3/smp.py
cppa3/unify.py
cppa3/view.py
cppa3.egg-info/PKG-INFO
cppa3.egg-info/SOURCES.txt
cppa3.egg-info/dependency_links.txt
cppa3.egg-info/not-zip-safe
cppa3.egg-info/requires.txt
cppa3.egg-info/top_level.txt
tests/catalog.py
tests/catalog.xml
tests/conftest.py
tests/test_cpa2.py
tests/test_cppa23.py
tests/test_index.py
tests/test_match.py
tests/test_pmode.py
tests/test_profile.py
tests/test_schema.py
tests/test_smp.py
tests/test_unify.py
tests/test_view.py
tests/cached_imported_xsds/ebbp-2.0.4.xsd
tests/cached_imported_xsds/ebcore-xmldsig1-schema.xsd
tests/cached_imported_xsds/ebms-header-3_0-200704_refactored.xsd
tests/cached_imported_xsds/ebms-multihop-1_0-200902_refactored.xsd
tests/cached_imported_xsds/ws-addr.xsd
tests/cached_imported_xsds/ws-securitypolicy-1.2.xsd
tests/cached_imported_xsds/ws-securitypolicy-1.3.xsd
tests/cached_imported_xsds/xenc-schema.xsd
tests/cached_imported_xsds/xkms.xsd
tests/cached_imported_xsds/xml.xsd
tests/cached_imported_xsds/xmldsig-core-schema.xsd
tests/cached_imported_xsds/xmldsig1-schema.xsd
tests/cached_imported_xsds/xmldsig11-schema.xsd
tests/config/channelprofiles.xml
tests/data/aap.xml
tests/data/cpp_a_0001.xml
tests/data/cpp_a_0001_sav.xml
tests/data/cpp_a_0002.xml
tests/data/cpp_a_0003.xml
tests/data/cpp_a_0007.xml
tests/data/cpp_a_0008.xml
tests/data/cpp_a_0009.xml
tests/data/cpp_a_0010.xml
tests/data/cpp_a_0011.xml
tests/data/cpp_a_0012.xml
tests/data/cpp_a_0013.xml
tests/data/cpp_a_0014.xml
tests/data/cpp_a_0015.xml
tests/data/cpp_a_0016.xml
tests/data/cpp_a_0017.xml
tests/data/cpp_a_0018.xml
tests/data/cpp_a_0019.xml
tests/data/cpp_a_0020.xml
tests/data/cpp_a_0021.xml
tests/data/cpp_a_0022.xml
tests/data/cpp_a_0023.xml
tests/data/cpp_a_0024.xml
tests/data/cpp_a_0026.xml
tests/data/cpp_a_0027.xml
tests/data/cpp_a_0028.xml
tests/data/cpp_a_0030.xml
tests/data/cpp_a_0031.xml
