Metadata-Version: 1.1
Name: cppa3
Version: 0.43
Summary: Libraries for processing ebCore CPPA version 3 documents
Home-page: https://www.oasis-open.org/committees/document.php?document_id=57550
Author: Pim van der Eijk
Author-email: pvde@sonnenglanz.net
License: mit
Platform: UNKNOWN
Classifier: Development Status :: 4 - Beta
Classifier: Programming Language :: Python
Classifier: Intended Audience :: Developers
